pycounts_jlee2843/__init__.py
pycounts_jlee2843/plotting.py
pycounts_jlee2843/pycounts_jlee2843.py
pycounts_jlee2843-0.1.0.dist-info/LICENSE
pycounts_jlee2843-0.1.0.dist-info/METADATA
pycounts_jlee2843-0.1.0.dist-info/WHEEL
pycounts_jlee2843-0.1.0.dist-info/RECORD
