Metadata-Version: 2.1
Name: pycounts_jlee2843
Version: 0.1.0
Summary: Calculate word counts in a text file!
License: MIT
Author: Jenny Lee
Requires-Python: >=3.9,<4.0
Classifier: License :: OSI Approved :: MIT License
Classifier: Programming Language :: Python :: 3
Classifier: Programming Language :: Python :: 3.9
Classifier: Programming Language :: Python :: 3.10
Classifier: Programming Language :: Python :: 3.11
Classifier: Programming Language :: Python :: 3.12
Requires-Dist: matplotlib (>=3.8.2,<4.0.0)
